[
    {
      "Month": "June",
      "Year": 2023,
      "InvoiceAmt": 71911413
    },
    {
      "Month": "July",
      "Year": 2023,
      "InvoiceAmt": 63493335
    },
    {
      "Month": "August",
      "Year": 2023,
      "InvoiceAmt": 62773695
    },
    {
      "Month": "September",
      "Year": 2023,
      "InvoiceAmt": 48332352
    },
    {
      "Month": "October",
      "Year": 2023,
      "InvoiceAmt": 59630382
    },
    {
      "Month": "November",
      "Year": 2023,
      "InvoiceAmt": 94758308
    },
    {
      "Month": "December",
      "Year": 2023,
      "InvoiceAmt": 69681509
    },
    {
      "Month": "January",
      "Year": 2024,
      "InvoiceAmt": 61044000
    },
    {
      "Month": "February",
      "Year": 2024,
      "InvoiceAmt": 60594823
    },
    {
      "Month": "March",
      "Year": 2024,
      "InvoiceAmt": 58754873
    },
    {
      "Month": "April",
      "Year": 2024,
      "InvoiceAmt": 62453314
    },
    {
      "Month": "May",
      "Year": 2024,
      "InvoiceAmt": 66495502
    },
    {
      "Month": "June",
      "Year": 2024,
      "InvoiceAmt": 67704546,
      "PredictedAmt": 67704546
    },
    {
      "Month": "July",
      "Year": 2024,
      "PredictedAmt": 64996726
    },
    {
      "Month": "August",
      "Year": 2024,
      "PredictedAmt": 64310651
    }
  ]